nonebot_plugins_jm_html/__init__.py
nonebot_plugins_jm_html/config.py
nonebot_plugins_jm_html/fetcher.py
nonebot_plugins_jm_html/handlers.py
nonebot_plugins_jm_html/routers.py
nonebot_plugins_jm_html/service.py
nonebot_plugins_jm_html/templates.py
nonebot_plugins_jm_html-1.0.8.dist-info/licenses/LICENSE
nonebot_plugins_jm_html-1.0.8.dist-info/METADATA
nonebot_plugins_jm_html-1.0.8.dist-info/WHEEL
nonebot_plugins_jm_html-1.0.8.dist-info/top_level.txt
nonebot_plugins_jm_html-1.0.8.dist-info/RECORD
