Metadata-Version: 2.4
Name: nonebot-plugins-jm-html
Version: 1.0.8
Summary: Generate mobile-first Bootstrap HTML pages for JM albums in NoneBot2, with temporary cache & optional password
Author-email: jaykserks <jaykserks@gmail.com>
License: The MIT License (MIT)
Project-URL: Homepage, https://github.com/kserksi/nonebot-plugin-jm-html
Project-URL: Repository, https://github.com/kserksi/nonebot-plugin-jm-html
Project-URL: Issues, https://github.com/kserksi/nonebot-plugin-jm-html/issues
Keywords: nonebot2,plugin,jmcomic,bootstrap,html,gallery
Classifier: Programming Language :: Python :: 3
Classifier: License :: OSI Approved :: MIT License
Classifier: Operating System :: OS Independent
Classifier: Framework :: AsyncIO
Requires-Python: >=3.9
License-File: LICENSE
Requires-Dist: nonebot2>=2.0
Requires-Dist: fastapi>=0.95
Requires-Dist: pydantic<3.0,>=2.0
Requires-Dist: jmcomic>=2.5.0
Requires-Dist: pydantic-settings>=2.0.0
Requires-Dist: pillow>=11.0.0
Requires-Dist: commonx>=0.6.38
Dynamic: license-file
